LICENSE
MANIFEST.in
README.md
setup.cfg
setup.py
versioneer.py
ashlar/__init__.py
ashlar/_version.py
ashlar/filepattern.py
ashlar/fileseries.py
ashlar/reg.py
ashlar/thumbnail.py
ashlar/transform.py
ashlar/utils.py
ashlar/viewer.py
ashlar/zen.py
ashlar.egg-info/PKG-INFO
ashlar.egg-info/SOURCES.txt
ashlar.egg-info/dependency_links.txt
ashlar.egg-info/entry_points.txt
ashlar.egg-info/not-zip-safe
ashlar.egg-info/requires.txt
ashlar.egg-info/top_level.txt
ashlar/jars/bioformats_package.jar
ashlar/scripts/__init__.py
ashlar/scripts/ashlar.py
ashlar/scripts/make_alignment_movie.py
ashlar/scripts/preview_slide.py