Metadata-Version: 2.1
Name: ashlar
Version: 1.19.0
Summary: Alignment by Simultaneous Harmonization of Layer/Adjacency Registration
Home-page: https://github.com/sorgerlab/ashlar
Download-URL: https://github.com/sorgerlab/ashlar/archive/v1.19.0.tar.gz
Author: Jeremy Muhlich
Author-email: jeremy_muhlich@hms.harvard.edu
License: MIT License
Keywords: scripts,microscopy,registration,stitching
Platform: UNKNOWN
Classifier: Development Status :: 5 - Production/Stable
Classifier: Intended Audience :: End Users/Desktop
Classifier: Intended Audience :: Science/Research
Classifier: License :: OSI Approved :: MIT License
Classifier: Natural Language :: English
Classifier: Operating System :: OS Independent
Classifier: Programming Language :: Python :: 3
Classifier: Topic :: Scientific/Engineering :: Visualization
License-File: LICENSE
